licensespring_hardware_id_generator-1.4.0.dist-info/RECORD
licensespring_hardware_id_generator-1.4.0.dist-info/WHEEL
licensespring_hardware_id_generator-1.4.0.dist-info/top_level.txt
licensespring_hardware_id_generator-1.4.0.dist-info/METADATA
licensespring_hardware_id_generator-1.4.0.dist-info/licenses/LICENSE
licensespring_hardware_id_generator/__init__.py
licensespring_hardware_id_generator/lib/libhardware_id_generator.so
