Metadata-Version: 2.1
Name: licensespring_hardware_id_generator
Version: 1.4.0
Summary: LicenseSpring hardware ID generator
License: LicenseSpring Hardware ID Generator License Agreement (LHIGLA)
Classifier: License :: Other/Proprietary License
Classifier: Programming Language :: Python :: 3
Classifier: Operating System :: OS Independent
License-File: LICENSE
